adafruit_ch9328/ch9328.py
adafruit_ch9328/ch9328_keymap.py
adafruit_circuitpython_ch9328-1.0.6.dist-info/licenses/LICENSE
adafruit_circuitpython_ch9328-1.0.6.dist-info/METADATA
adafruit_circuitpython_ch9328-1.0.6.dist-info/WHEEL
adafruit_circuitpython_ch9328-1.0.6.dist-info/top_level.txt
adafruit_circuitpython_ch9328-1.0.6.dist-info/RECORD
