Metadata-Version: 2.4
Name: adafruit-circuitpython-ch9328
Version: 1.0.6
Summary: CircuitPython driver for the CH9328 UART to HID keyboard breakout
Author-email: Adafruit Industries <circuitpython@adafruit.com>
License: MIT
Project-URL: Homepage, https://github.com/adafruit/Adafruit_CircuitPython_CH9328
Keywords: adafruit,blinka,circuitpython,micropython,ch9328,UART
Classifier: Intended Audience :: Developers
Classifier: Topic :: Software Development :: Libraries
Classifier: Topic :: Software Development :: Embedded Systems
Classifier: Topic :: System :: Hardware
Classifier: License :: OSI Approved :: MIT License
Classifier: Programming Language :: Python :: 3
License-File: LICENSE
Requires-Dist: Adafruit-Blinka
Requires-Dist: pyserial
Provides-Extra: optional
Dynamic: license-file
